pikopenapi
