Metadata-Version: 2.1
Name: pik-openapi
Version: 1.0.3
Summary: PIK DRF openapi extensions
Home-page: https://github.com/pik-software/pik-openapi
Author: pik-software
Author-email: no-reply@pik-software.ru
License: UNKNOWN
Project-URL: Bug Reports, https://github.com/pik-software/pik-openapi/issues
Project-URL: Funding, https://github.com/pik-software/pik-openapi
Project-URL: Source, https://github.com/pik-software/pik-openapi
Keywords: pik django drf rest openapi
Platform: UNKNOWN
Classifier: Development Status :: 5 - Production/Stable
Classifier: Intended Audience :: Developers
Classifier: Topic :: Software Development :: Build Tools
Classifier: License :: OSI Approved :: MIT License
Classifier: Programming Language :: Python :: 3.6
Requires-Python: ~=3.6
Provides-Extra: dev
License-File: LICENSE
